toolbox/__init__.py
toolbox/cfg.py
toolbox/cli.py
toolbox/dfa.py
toolbox/nfa.py
toolbox/parser.py
toolbox/pda.py
toolbox/templates.py
automata_toolbox-2.0.dist-info/METADATA
automata_toolbox-2.0.dist-info/WHEEL
automata_toolbox-2.0.dist-info/entry_points.txt
automata_toolbox-2.0.dist-info/top_level.txt
automata_toolbox-2.0.dist-info/RECORD
