Metadata-Version: 2.2
Name: automata_toolbox
Version: 2.0
Summary: A Python CLI for DFA, NFA, PDA, and CFG simulation
Home-page: https://github.com/Cris24dc/Automata-Toolbox.git
Author: Andrei Cristian-David
Author-email: cristianandrei752@gmail.com
Classifier: Programming Language :: Python :: 3
Classifier: Operating System :: OS Independent
Requires-Python: >=3.7
Dynamic: author
Dynamic: author-email
Dynamic: classifier
Dynamic: description
Dynamic: description-content-type
Dynamic: home-page
Dynamic: requires-python
Dynamic: summary
